fountain_sdk/__init__.py
fountain_sdk/client.py
fountain_sdk/exceptions.py
fountain_sdk/models.py
fountain_sdk-1.0.1.dist-info/licenses/LICENSE
fountain_sdk-1.0.1.dist-info/METADATA
fountain_sdk-1.0.1.dist-info/WHEEL
fountain_sdk-1.0.1.dist-info/top_level.txt
fountain_sdk-1.0.1.dist-info/RECORD
