Metadata-Version: 2.4
Name: fountain-sdk
Version: 1.0.1
Summary: Python SDK for Fountain stablecoin API
Home-page: https://github.com/xrpl-fountain/fountain-sdk-python
Author: Fountain Team
Author-email: Fountain Team <support@fountain.com>
License: MIT
Project-URL: Homepage, https://github.com/xrpl-fountain/fountain-sdk-python
Project-URL: Repository, https://github.com/xrpl-fountain/fountain-sdk-python
Project-URL: Issues, https://github.com/xrpl-fountain/fountain-sdk-python/issues
Classifier: Development Status :: 4 - Beta
Classifier: Intended Audience :: Developers
Classifier: License :: OSI Approved :: MIT License
Classifier: Programming Language :: Python :: 3
Classifier: Programming Language :: Python :: 3.8
Classifier: Programming Language :: Python :: 3.9
Classifier: Programming Language :: Python :: 3.10
Classifier: Programming Language :: Python :: 3.11
Requires-Python: >=3.8
License-File: LICENSE
Requires-Dist: requests>=2.31.0
Provides-Extra: dev
Requires-Dist: pytest>=7.4.0; extra == "dev"
Requires-Dist: pytest-cov>=4.1.0; extra == "dev"
Requires-Dist: black>=23.7.0; extra == "dev"
Requires-Dist: mypy>=1.5.0; extra == "dev"
Dynamic: author
Dynamic: home-page
Dynamic: license-file
Dynamic: requires-python
